src/example_package_guitaek/__init__.py
src/example_package_guitaek/example.py
levenstein-0.0.2.dist-info/METADATA
levenstein-0.0.2.dist-info/WHEEL
levenstein-0.0.2.dist-info/licenses/LICENSE
levenstein-0.0.2.dist-info/RECORD
