Metadata-Version: 2.1
Name: levenstein
Version: 0.0.2
Summary: Download Levenshtein instead
Project-URL: source, https://github.com/GuiTaek/levenstein
Author-email: GuiTaek <GuiTaekM@gmail.com>
License-File: LICENSE
Classifier: License :: OSI Approved :: MIT License
Classifier: Operating System :: OS Independent
Classifier: Programming Language :: Python :: 3
Requires-Python: <3.7,>3.7
